wait_for_it_to/__init__.py
wait_for_it_to/_version.py
wait_for_it_to-0.0.21.dist-info/LICENSE
wait_for_it_to-0.0.21.dist-info/METADATA
wait_for_it_to-0.0.21.dist-info/WHEEL
wait_for_it_to-0.0.21.dist-info/top_level.txt
wait_for_it_to-0.0.21.dist-info/RECORD
